mongobackup/__init__.py
mongobackup/backups.py
mongobackup/s3.py
mongobackup/shell.py
mongobackup-0.3.0.dist-info/licenses/LICENSE
mongobackup-0.3.0.dist-info/METADATA
mongobackup-0.3.0.dist-info/WHEEL
mongobackup-0.3.0.dist-info/top_level.txt
mongobackup-0.3.0.dist-info/RECORD
