Metadata-Version: 2.4
Name: mongobackup
Version: 0.3.0
Summary: A library to manage mongo backups and restoration from backup
Author-email: "Zagaran, Inc." <info@zagaran.com>
License-Expression: MIT
Project-URL: Homepage, https://github.com/zagaran/mongobackup
Keywords: mongo,mongodb,database,backup
Classifier: Development Status :: 4 - Beta
Classifier: Operating System :: MacOS :: MacOS X
Classifier: Operating System :: Microsoft :: Windows
Classifier: Operating System :: POSIX
Classifier: Programming Language :: Python
Classifier: Topic :: Database
Requires-Python: >=3.6
License-File: LICENSE
Requires-Dist: boto>=2.25
Dynamic: license-file
